image_processing/__init__.py
image_processing/processing/__init__.py
image_processing/processing/combination.py
image_processing/processing/transformation.py
image_processing/utils/__init__.py
image_processing/utils/io.py
image_processing/utils/plot.py
ozzy_image_processing-0.0.3.dist-info/METADATA
ozzy_image_processing-0.0.3.dist-info/WHEEL
ozzy_image_processing-0.0.3.dist-info/top_level.txt
ozzy_image_processing-0.0.3.dist-info/RECORD
